[
  {
    "title": "The Quiet Death of Ello's Big Dreams - Waxy.org",
    "description": "Interesting recap of the history and death of the social network Ello.",
    "link": "https://waxy.org/2024/01/the-quiet-death-of-ellos-big-dreams/",
    "dateShared": "2024-02-02T04:44:00.000Z",
    "guid": "619f4ec1-a941-469f-bed2-cbf930fa0b60",
    "slug": "the-quiet-death-of-ellos-big-dreams"
  },
  {
    "title": "feedle: Search and Discover Quality RSS Feeds",
    "description": "A handy site for discovering RSS feeds for blogs and podcasts.",
    "link": "https://feedle.world/",
    "dateShared": "2024-02-04T21:27:24-05:00",
    "guid": "df243177-0037-4df2-892d-f0f2db158dab",
    "slug": "feedle-search-and-discover-quality-rss-feeds"
  },
  {
    "title": "Styling an RSS Feed With XSLT",
    "description": "A helpful article that I used to style my RSS feeds.",
    "link": "https://natclark.com/tutorials/xslt-style-rss-feed/",
    "dateShared": "2024-02-10T02:03:53-05:00",
    "guid": "16414245-8ed1-49af-8257-80162e15c55d",
    "slug": "styling-an-rss-feed-with-xslt"
  },
  {
    "title": "Own Your Web - Issue 9: We ❤️ RSS",
    "description": "A thorough but easy to understand rundown of RSS. Helpful for folks new to RSS, and a good read even for those familiar.",
    "link": "https://buttondown.email/ownyourweb/archive/issue-09/",
    "dateShared": "2024-02-12T23:03:21-05:00",
    "guid": "EBE4717F-8DB7-479F-AF85-5D19BDF3575B",
    "slug": "own-your-web-issue-9-we-rss-buttondown"
  },
  {
    "title": "Own Your Web - Issue 1: Your Superpower",
    "description": "More encouragement to make a personal website. Do it!",
    "link": "https://buttondown.email/ownyourweb/archive/issue-01/",
    "dateShared": "2024-02-14T00:02:03-05:00",
    "guid": "A330F736-55FB-4630-8AEB-47EFF0443677",
    "slug": "own-your-web-issue-1-your-superpower-buttondown"
  },
  {
    "title": "Sorting Git branches",
    "description": "Cassidy Williams shares a quick post on how to sort git branches, something I'd never even thought to look into despite definitely needing sometimes!",
    "link": "https://blog.cassidoo.co/post/sort-git-branch/",
    "dateShared": "2024-02-20T01:45:51-05:00",
    "guid": "A3AB536E-AFE6-4828-A5FE-D51D1DC73851",
    "slug": "sorting-git-branches"
  },
  {
    "title": "Old games consoles aren’t redundant – I think they’re a fantastic must-buy | Stuff",
    "description": "Craig Grannell on the benefits of buying and owning game consoles past their 'prime'. I wholeheartedly agree. @craiggrannell",
    "link": "https://www.stuff.tv/features/old-games-consoles-arent-redundant-i-think-theyre-a-boon/",
    "dateShared": "2024-02-25T10:10:50-05:00",
    "guid": "4A3C75FA-B131-424C-83E6-FACB51676B5F",
    "slug": "old-games-consoles-aren-t-redundant"
  },
  {
    "title": "RsS iS dEaD LOL",
    "description": "This utility lets you enter your Fediverse handle and find RSS feeds in your network. Very simple and clean UI, and super useful if you're looking for some more feeds for your RSS reader.",
    "link": "https://rss-is-dead.lol/",
    "dateShared": "2024-03-01T23:43:14-05:00",
    "guid": "A386E108-4ED5-4BD2-999B-E9EF61A335EB",
    "slug": "rss-is-dead-lol"
  },
  {
    "title": "Base CSS for your text-based pages",
    "description": "Cassidy Williams offers a simple block of CSS that makes a barebones website look nice without having to do a bunch of custom fancy styles.",
    "link": "https://blog.cassidoo.co/post/base-css/",
    "dateShared": "2024-03-03T18:18:02-05:00",
    "guid": "A596A389-2B6C-4909-A2C9-36F6EA9E5C88",
    "slug": "base-css-for-your-text-based-pages"
  },
  {
    "title": "How HEAD works in git",
    "description": "A crystal clear explanation of how HEAD works in git. I think this can get glossed over by many regular users, so it's good to have an understanding of it.",
    "link": "https://jvns.ca/blog/2024/03/08/how-head-works-in-git/",
    "dateShared": "2024-03-25T10:02:04-04:00",
    "guid": "131494E5-09E1-4224-8AF2-590925F1485A",
    "slug": "how-head-works-in-git"
  },
  {
    "title": "A Temporary Design",
    "description": "Dave Plummer designed a temporary Format dialog for Windows 30 years ago, and it hasn't been changed yet! Here's a tweet thread with the story.",
    "link": "https://x.com/davepl1968/status/1772042158046146792?s=12",
    "dateShared": "2024-03-26T18:29:54-04:00",
    "guid": "846FB5EC-7077-4CFA-8D65-C8A2831E7B51",
    "slug": "temporary-format-dialog-design"
  },
  {
    "title": "If this one guy got hit by a bus, the world's software would fall apart.",
    "description": "The sheer amount of software and services that exist while depending on the thankless, volunteer work of individuals or tiny teams is terrifying.",
    "link": "https://lunduke.locals.com/post/5477752/if-this-one-guy-got-hit-by-a-bus-the-worlds-software-would-fall-apart",
    "dateShared": "2024-04-15T11:28:46-04:00",
    "guid": "50E1988B-F267-4739-997D-2A5F94E74B82",
    "slug": "if-this-one-guy-got-hit-by-a-bus-the-world-s-software-would-fall-apart-"
  }
]
